cleverhans/__init__.py
cleverhans/utils.py
cleverhans/devtools/__init__.py
cleverhans/devtools/autopep8_all.py
cleverhans/devtools/checks.py
cleverhans/devtools/list_files.py
cleverhans/devtools/mocks.py
cleverhans/devtools/version.py
cleverhans/devtools/tests/__init__.py
cleverhans/devtools/tests/test_format.py
cleverhans/experimental/__init__.py
cleverhans/experimental/certification/__init__.py
cleverhans/experimental/certification/certify.py
cleverhans/experimental/certification/dual_formulation.py
cleverhans/experimental/certification/nn.py
cleverhans/experimental/certification/optimization.py
cleverhans/experimental/certification/utils.py
cleverhans/jax/__init__.py
cleverhans/jax/utils.py
cleverhans/jax/attacks/__init__.py
cleverhans/jax/attacks/fast_gradient_method.py
cleverhans/jax/attacks/projected_gradient_descent.py
cleverhans/plot/__init__.py
cleverhans/plot/image.py
cleverhans/plot/pyplot_defaults.py
cleverhans/plot/pyplot_image.py
cleverhans/plot/save_pdf.py
cleverhans/plot/success_fail.py
cleverhans/tf2/__init__.py
cleverhans/tf2/utils.py
cleverhans/tf2/attacks/__init__.py
cleverhans/tf2/attacks/basic_iterative_method.py
cleverhans/tf2/attacks/carlini_wagner_l2.py
cleverhans/tf2/attacks/fast_gradient_method.py
cleverhans/tf2/attacks/madry_et_al.py
cleverhans/tf2/attacks/momentum_iterative_method.py
cleverhans/tf2/attacks/projected_gradient_descent.py
cleverhans/tf2/attacks/spsa.py
cleverhans/torch/__init__.py
cleverhans/torch/utils.py
cleverhans/torch/attacks/__init__.py
cleverhans/torch/attacks/carlini_wagner_l2.py
cleverhans/torch/attacks/fast_gradient_method.py
cleverhans/torch/attacks/hop_skip_jump_attack.py
cleverhans/torch/attacks/noise.py
cleverhans/torch/attacks/projected_gradient_descent.py
cleverhans/torch/attacks/semantic.py
cleverhans/torch/attacks/sparse_l1_descent.py
cleverhans/torch/attacks/spsa.py
cleverhans/torch/tests/__init__.py
cleverhans/torch/tests/test_attacks.py
cleverhans/torch/tests/test_utils.py
cleverhans-4.0.0.dist-info/LICENSE
cleverhans-4.0.0.dist-info/METADATA
cleverhans-4.0.0.dist-info/WHEEL
cleverhans-4.0.0.dist-info/top_level.txt
cleverhans-4.0.0.dist-info/RECORD
